fastapi_authly/__about__.py
fastapi_authly/__init__.py
fastapi_authly/auth.py
fastapi_authly/charts.py
fastapi_authly/deps.py
fastapi_authly/docs.py
fastapi_authly/interfaces.py
fastapi_authly/contrib/__init__.py
fastapi_authly/contrib/tortoise_pg.py
fastapi_authly/core/__init__.py
fastapi_authly/core/config.py
fastapi_authly/core/security.py
fastapi_authly/models/__init__.py
fastapi_authly/models/user.py
fastapi_authly/schemas/__init__.py
fastapi_authly/schemas/user.py
fastapi_authly/static/echarts.min.js
fastapi_authly/static/favicon.svg
fastapi_authly/static/scalar/standalone.js
fastapi_authly/static/scalar/style.css
fastapi_authly-0.1.5.dist-info/METADATA
fastapi_authly-0.1.5.dist-info/WHEEL
fastapi_authly-0.1.5.dist-info/licenses/LICENSE
fastapi_authly-0.1.5.dist-info/RECORD
