Metadata-Version: 2.4
Name: fastapi-authly
Version: 0.1.5
Summary: A modular authentication system for FastAPI with OAuth2, JWT, and password recovery
Project-URL: Homepage, https://github.com/yourusername/fastapi-auth-module
Project-URL: Documentation, https://yourusername.github.io/fastapi-auth-module/
Project-URL: Repository, https://github.com/yourusername/fastapi-auth-module
Project-URL: Issues, https://github.com/yourusername/fastapi-auth-module/issues
Project-URL: Changelog, https://github.com/yourusername/fastapi-auth-module/blob/main/CHANGELOG.md
Author-email: Lang Xu <langxu2023@outlook.com>
Maintainer-email: Lang Xu <langxu2023@outlook.com>
License: MIT
License-File: LICENSE
Keywords: authentication,fastapi,jwt,login,modular,oauth2,security
Classifier: Development Status :: 3 - Alpha
Classifier: Framework :: FastAPI
Classifier: Intended Audience :: Developers
Classifier: License :: OSI Approved :: MIT License
Classifier: Programming Language :: Python :: 3
Classifier: Programming Language :: Python :: 3.8
Classifier: Programming Language :: Python :: 3.9
Classifier: Programming Language :: Python :: 3.10
Classifier: Programming Language :: Python :: 3.11
Classifier: Programming Language :: Python :: 3.12
Classifier: Topic :: Internet :: WWW/HTTP :: Session
Classifier: Topic :: Security
Requires-Python: >=3.10
Requires-Dist: asyncpg>=0.31.0
Requires-Dist: emails>=0.6.0
Requires-Dist: fastapi>=0.100.0
Requires-Dist: jinja2>=3.0.0
Requires-Dist: jwt>=1.3.1
Requires-Dist: passlib[bcrypt]>=1.7.4
Requires-Dist: pydantic-settings>=2.1.0
Requires-Dist: pydantic[email]>=2.0.0
Requires-Dist: python-jose[cryptography]>=3.3.0
Requires-Dist: python-multipart>=0.0.6
Requires-Dist: tortoise-orm[psycopg]>=0.25.3
Requires-Dist: uvicorn>=0.40.0
Provides-Extra: charts
Requires-Dist: selenium>=4.0.0; extra == 'charts'
Provides-Extra: docs
Requires-Dist: mkdocs-material>=9.0.0; extra == 'docs'
Requires-Dist: mkdocs>=1.5.0; extra == 'docs'
Provides-Extra: sqlalchemy
Requires-Dist: alembic>=1.12.0; extra == 'sqlalchemy'
Requires-Dist: sqlalchemy>=2.0.0; extra == 'sqlalchemy'
Provides-Extra: test
Requires-Dist: faker>=20.0.0; extra == 'test'
Requires-Dist: httpx>=0.25.0; extra == 'test'
Requires-Dist: pytest-asyncio>=0.21.0; extra == 'test'
Requires-Dist: pytest>=7.0.0; extra == 'test'
Provides-Extra: tortoise
Requires-Dist: tortoise-orm[asyncpg]>=0.20.0; extra == 'tortoise'
